mtpylon/__init__.py
mtpylon/constants.py
mtpylon/contextvars.py
mtpylon/exceptions.py
mtpylon/income_message.py
mtpylon/message_sender.py
mtpylon/py.typed
mtpylon/schema.py
mtpylon/serializers.py
mtpylon/types.py
mtpylon/utils.py
mtpylon/acknowledgement_store/__init__.py
mtpylon/acknowledgement_store/acknowledgement_store_protocol.py
mtpylon/acknowledgement_store/inmemory_acknowledgement_store.py
mtpylon/acknowledgement_store/types.py
mtpylon/aiohandlers/__init__.py
mtpylon/aiohandlers/pub_keys.py
mtpylon/aiohandlers/schema.py
mtpylon/aiohandlers/types.py
mtpylon/aiohandlers/websockets.py
mtpylon/configuration/__init__.py
mtpylon/configuration/configure.py
mtpylon/configuration/constants.py
mtpylon/configuration/import_path.py
mtpylon/configuration/types.py
mtpylon/crypto/__init__.py
mtpylon/crypto/auth_key.py
mtpylon/crypto/auth_key_manager.py
mtpylon/crypto/exceptions.py
mtpylon/crypto/generate_key_iv.py
mtpylon/crypto/get_msg_key.py
mtpylon/crypto/key_iv_pair.py
mtpylon/crypto/random_prime.py
mtpylon/crypto/rsa.py
mtpylon/crypto/rsa_fingerprint.py
mtpylon/crypto/rsa_manager.py
mtpylon/dh_prime_generators/__init__.py
mtpylon/dh_prime_generators/single_prime.py
mtpylon/dh_prime_generators/two_ton.py
mtpylon/dh_prime_generators/typing.py
mtpylon/message_handler/__init__.py
mtpylon/message_handler/message_handler.py
mtpylon/message_handler/strategies/__init__.py
mtpylon/message_handler/strategies/handle_message_container.py
mtpylon/message_handler/strategies/handle_msgs_ack_message.py
mtpylon/message_handler/strategies/handle_rpc_query_message.py
mtpylon/message_handler/strategies/handle_unencrypted_message.py
mtpylon/message_handler/strategies/handle_unknown_message.py
mtpylon/message_handler/strategies/logging_adapter.py
mtpylon/message_handler/strategies/selector.py
mtpylon/message_handler/strategies/types.py
mtpylon/message_handler/strategies/utils.py
mtpylon/messages/__init__.py
mtpylon/messages/encrypted_message.py
mtpylon/messages/mtproto_message.py
mtpylon-0.0.3.dist-info/LICENSE
mtpylon-0.0.3.dist-info/METADATA
mtpylon-0.0.3.dist-info/WHEEL
mtpylon-0.0.3.dist-info/top_level.txt
mtpylon-0.0.3.dist-info/RECORD
