Metadata-Version: 2.1
Name: mtpylon
Version: 0.0.3
Summary: Library to build backend with MTProto protocol
Home-page: https://github.com/Zapix/mtpylon
Author: Aleksandr Aibulatov
Author-email: zap.aibulatov@gmail.com
License: UNKNOWN
Platform: UNKNOWN
Classifier: Development Status :: 1 - Planning
Classifier: Programming Language :: Python :: 3.9
Classifier: Framework :: AsyncIO
Classifier: License :: OSI Approved :: MIT License
Classifier: Operating System :: OS Independent
Requires-Python: >=3.9
License-File: LICENSE
Requires-Dist: aiohttp (>=3.7.4)
Requires-Dist: aiohttp-cors (>=0.7.0)
Requires-Dist: rsa (>=4.7.2)
Requires-Dist: TgCrypto (>=1.2.2)
Requires-Dist: pyaes (>=1.6.1)
Requires-Dist: mypy-extensions (>=0.4.3)
